neurostrip/__init__.py
neurostrip/lib.py
neurostrip/main.py
neurostrip-1.0.1.dist-info/licenses/LICENSE
neurostrip-1.0.1.dist-info/METADATA
neurostrip-1.0.1.dist-info/WHEEL
neurostrip-1.0.1.dist-info/entry_points.txt
neurostrip-1.0.1.dist-info/top_level.txt
neurostrip-1.0.1.dist-info/RECORD
